rqalpha_mod_shipane/VERSION.txt
rqalpha_mod_shipane/__init__.py
rqalpha_mod_shipane/mod.py
rqalpha_mod_shipane-0.4.0.dist-info/DESCRIPTION.rst
rqalpha_mod_shipane-0.4.0.dist-info/METADATA
rqalpha_mod_shipane-0.4.0.dist-info/RECORD
rqalpha_mod_shipane-0.4.0.dist-info/WHEEL
rqalpha_mod_shipane-0.4.0.dist-info/metadata.json
rqalpha_mod_shipane-0.4.0.dist-info/top_level.txt
