Metadata-Version: 2.0
Name: rqalpha-mod-shipane
Version: 0.4.0
Summary: RQAlpha Mod ShipanE to support stock real time trading
Home-page: https://github.com/wh1100717/rqalpha-mod-ShiPanE
Author: wh1100717
Author-email: me@emptystack.net
License: Apache License v2
Platform: UNKNOWN
Classifier: Programming Language :: Python
Classifier: Operating System :: Microsoft :: Windows
Classifier: Operating System :: Unix
Classifier: Programming Language :: Python :: 3.5
Classifier: Programming Language :: Python :: 3.6
Requires-Dist: lxml (==3.6.4)
Requires-Dist: rqalpha (>=3.0.1)
Requires-Dist: shipane-sdk (>=1.0.0b5)
